shopify_requests/__init__.py
shopify_requests/rest_client.py
shopify_requests-0.4.0.dist-info/LICENSE
shopify_requests-0.4.0.dist-info/WHEEL
shopify_requests-0.4.0.dist-info/METADATA
shopify_requests-0.4.0.dist-info/RECORD
